{"_type":"export","__export_format":4,"__export_date":"2024-04-24T21:49:43.853Z","__export_source":"insomnia.desktop.app:v9.0.0","resources":[{"_id":"req_c55a6b3250da448caf1f187cc2745f9d","parentId":"fld_f35b3cb1a4d14732810e88a8bdccbce1","modified":1713995346221,"created":1713994955134,"url":"{{ _.base_url }}/produto","name":"List","description":"","method":"GET","body":{},"preRequestScript":"","parameters":[],"headers":[{"name":"User-Agent","value":"insomnia/9.0.0"}],"authentication":{},"metaSortKey":-1713995312304.25,"isPrivate":false,"pathParameters":[],"settingStoreCookies":true,"settingSendCookies":true,"settingDisableRenderRequestBody":false,"settingEncodeUrl":true,"settingRebuildPath":true,"settingFollowRedirects":"global","_type":"request"},{"_id":"fld_f35b3cb1a4d14732810e88a8bdccbce1","parentId":"wrk_f86e141d74ba498c99e771afdc14bd54","modified":1713995309348,"created":1713995309348,"name":"Produto","description":"","environment":{},"environmentPropertyOrder":null,"metaSortKey":-1713995309348,"_type":"request_group"},{"_id":"wrk_f86e141d74ba498c99e771afdc14bd54","parentId":null,"modified":1713994924658,"created":1713994924658,"name":"WA-RESTful_API","description":"","scope":"collection","_type":"workspace"},{"_id":"req_104326520155493c8e4a57c7087928f2","parentId":"fld_f35b3cb1a4d14732810e88a8bdccbce1","modified":1713995351396,"created":1713994956696,"url":"{{ _.base_url }}/produto","name":"Create","description":"","method":"POST","body":{"mimeType":"application/json","text":"{\n\t\"nome\": \"{% faker 'commerce', '', '', '', 'product', '', '', '', '', '', '', '', '', '', '', '', '', '', '', '', '', '', '', '', '', '', 'en' %}\",\n\t\"preco\": {% faker 'commerce', '', '', '', 'price', '', '', '', '', '', '', '', '', '', '', '', '', '', '', '', '', '', '', '', '', '', 'en' %},\n\t\"estoque\": {% faker 'random', '', '', '', '', '', '', '', '', '', '', '', '', '', '', '', '', '', '', '', 'numeric', '', '', '', '', '', 'en' %}\n}"},"preRequestScript":"","parameters":[],"headers":[{"name":"Content-Type","value":"application/json"},{"name":"User-Agent","value":"insomnia/9.0.0"}],"authentication":{},"metaSortKey":-1713995312305.8125,"isPrivate":false,"pathParameters":[],"settingStoreCookies":true,"settingSendCookies":true,"settingDisableRenderRequestBody":false,"settingEncodeUrl":true,"settingRebuildPath":true,"settingFollowRedirects":"global","_type":"request"},{"_id":"req_55efa66f8c2c4ed1916fc35d4c14f604","parentId":"fld_f35b3cb1a4d14732810e88a8bdccbce1","modified":1713995356293,"created":1713994957829,"url":"{{ _.base_url }}/produto/9b6d0222-00e9-4a58-b5ae-4f62a71b691f","name":"Read","description":"","method":"GET","body":{},"preRequestScript":"","parameters":[],"headers":[{"name":"User-Agent","value":"insomnia/9.0.0"}],"authentication":{},"metaSortKey":-1713995312306.2031,"isPrivate":false,"pathParameters":[],"settingStoreCookies":true,"settingSendCookies":true,"settingDisableRenderRequestBody":false,"settingEncodeUrl":true,"settingRebuildPath":true,"settingFollowRedirects":"global","_type":"request"},{"_id":"req_bd16eeb204ee4ecbb0477a10c9d1d1bc","parentId":"fld_f35b3cb1a4d14732810e88a8bdccbce1","modified":1713995353027,"created":1713994958816,"url":"{{ _.base_url }}/produto/212aa0aa-992f-4a22-929f-c9b44b2028ed","name":"Update","description":"","method":"PUT","body":{"mimeType":"application/json","text":"{\n\t\"nome\": \"New Name\",\n\t\"preco\": 14.99,\n\t\"estoque\": 20\n}"},"preRequestScript":"","parameters":[],"headers":[{"name":"Content-Type","value":"application/json"},{"name":"User-Agent","value":"insomnia/9.0.0"}],"authentication":{},"metaSortKey":-1713995312306.5938,"isPrivate":false,"pathParameters":[],"settingStoreCookies":true,"settingSendCookies":true,"settingDisableRenderRequestBody":false,"settingEncodeUrl":true,"settingRebuildPath":true,"settingFollowRedirects":"global","_type":"request"},{"_id":"req_97e4f25e7c874b0ab38f051766ce5758","parentId":"fld_f35b3cb1a4d14732810e88a8bdccbce1","modified":1713995348049,"created":1713995006906,"url":"{{ _.base_url }}/produto/af7b73df-aadb-4188-be11-646e90b77e27","name":"Delete","description":"","method":"DELETE","body":{},"preRequestScript":"","parameters":[],"headers":[{"name":"User-Agent","value":"insomnia/9.0.0"}],"authentication":{},"metaSortKey":-1713995312307.375,"isPrivate":false,"pathParameters":[],"settingStoreCookies":true,"settingSendCookies":true,"settingDisableRenderRequestBody":false,"settingEncodeUrl":true,"settingRebuildPath":true,"settingFollowRedirects":"global","_type":"request"},{"_id":"env_d049c49f4bad8f5a2eb2a9f0121ba6b188dc19fb","parentId":"wrk_f86e141d74ba498c99e771afdc14bd54","modified":1713994986012,"created":1713994924659,"name":"Base Environment","data":{"base_url":"http://localhost:1000/v1"},"dataPropertyOrder":{"&":["base_url"]},"color":null,"isPrivate":false,"metaSortKey":1713994924659,"_type":"environment"},{"_id":"jar_d049c49f4bad8f5a2eb2a9f0121ba6b188dc19fb","parentId":"wrk_f86e141d74ba498c99e771afdc14bd54","modified":1713994924663,"created":1713994924663,"name":"Default Jar","cookies":[],"_type":"cookie_jar"}]}